README.md
setup.cfg
setup.py
qubo_nn/__init__.py
qubo_nn/config.py
qubo_nn/data.py
qubo_nn/gen_red_cfg.py
qubo_nn/logger.py
qubo_nn/main.py
qubo_nn/noisy_similarity_algo.py
qubo_nn/noisy_similarity_algo_all.py
qubo_nn/noisy_similarity_algo_multi.py
qubo_nn/noisy_similarity_algo_pairwise.py
qubo_nn/noisy_similarity_algo_pairwise2.py
qubo_nn/pipeline.py
qubo_nn.egg-info/PKG-INFO
qubo_nn.egg-info/SOURCES.txt
qubo_nn.egg-info/dependency_links.txt
qubo_nn.egg-info/not-zip-safe
qubo_nn.egg-info/requires.txt
qubo_nn.egg-info/top_level.txt
qubo_nn/nn/__init__.py
qubo_nn/nn/models.py
qubo_nn/plots/__init__.py
qubo_nn/plots/gen_big_arch_generalized.py
qubo_nn/plots/gen_big_arch_gi_sgi_mcq.py
qubo_nn/plots/gen_big_arch_qa_np_sp_m2sat.py
qubo_nn/plots/gen_def_a3.py
qubo_nn/plots/gen_gi_sgi_same.py
qubo_nn/plots/gen_large_arch_generalized.py
qubo_nn/plots/gen_m23sat.py
qubo_nn/plots/gen_m2sat_comp_pickle.py
qubo_nn/plots/gen_m2sat_three_case.py
qubo_nn/plots/gen_maxpool_comp.py
qubo_nn/plots/gen_mc_comp_edges.py
qubo_nn/plots/gen_np.py
qubo_nn/plots/gen_qa_comp.py
qubo_nn/plots/gen_qa_ones.py
qubo_nn/plots/gen_qa_zeros.py
qubo_nn/plots/gen_qb.py
qubo_nn/plots/gen_qk.py
qubo_nn/plots/gen_qubo_map_pickle.py
qubo_nn/plots/gen_red_ae.py
qubo_nn/plots/gen_reverse_loss_pickle.py
qubo_nn/plots/gen_sim.py
qubo_nn/plots/gen_sim_pair.py
qubo_nn/plots/gen_sim_pair2.py
qubo_nn/plots/gen_small_arch_generalized.py
qubo_nn/plots/gen_small_arch_gi_sgi_mcq.py
qubo_nn/plots/gen_small_arch_m2sat.py
qubo_nn/plots/gen_small_arch_sp.py
qubo_nn/plots/gen_sp_vars.py
qubo_nn/plots/gen_tot_mc_100_genX.py
qubo_nn/plots/gen_tot_mc_30_gen4.py
qubo_nn/plots/gen_tot_mc_gen4.py
qubo_nn/plots/gen_tot_mc_pickle.py
qubo_nn/plots/gen_tsne.py
qubo_nn/plots/gen_tsne_100_genX.py
qubo_nn/plots/gen_tsne_30_gen4.py
qubo_nn/plots/gen_tsne_gen4.py
qubo_nn/plots/gen_tsp_comp.py
qubo_nn/plots/labellines.py
qubo_nn/plots/lib.py
qubo_nn/plots/plot_big_arch_generalized.py
qubo_nn/plots/plot_big_arch_gi_sgi_mcq.py
qubo_nn/plots/plot_big_arch_qa_np_sp_m2sat.py
qubo_nn/plots/plot_def_a3.py
qubo_nn/plots/plot_gi_sgi_same.py
qubo_nn/plots/plot_m2sat_comp.py
qubo_nn/plots/plot_m2sat_comp_16x16_1M.py
