Metadata-Version: 2.1
Name: qubo-nn
Version: 0.2.5
Summary: QUBO translations for 14 problems. Also: Reverse-engeering and AutoEncoders for QUBOs.
Home-page: https://github.com/instance01/qubo-nn
Author: Instance01
Author-email: whodis@instancedev.com
License: MIT
Platform: UNKNOWN
Classifier: Development Status :: 3 - Alpha
Classifier: License :: OSI Approved :: MIT License
Classifier: Programming Language :: Python :: 3
Classifier: Topic :: Utilities
Classifier: Topic :: Scientific/Engineering :: Physics
Classifier: Topic :: Software Development :: Libraries
Classifier: Topic :: Scientific/Engineering :: Artificial Intelligence
Classifier: Intended Audience :: Science/Research
